{
  "description": "Manual catch-up — consolidation + triage drain with no interval minimum.",
  "processes": {
    "reflect": { "enabled": false },
    "distill": { "enabled": false },
    "consolidate": { "enabled": true, "allowedTypes": ["memory"], "maxChunkSize": 50, "minPoolSize": 0 },
    "memoryInference": { "enabled": false },
    "graphExtraction": { "enabled": false },
    "extract": { "enabled": false },
    "triage": { "enabled": true, "applyMode": "queue", "policy": "personal-stash", "maxAcceptsPerRun": 100 }
  },
  "sync": { "enabled": true, "push": true }
}
